kompoz/__init__.py
kompoz/_async.py
kompoz/_async_validation.py
kompoz/_caching.py
kompoz/_concurrency.py
kompoz/_core.py
kompoz/_predicate.py
kompoz/_registry.py
kompoz/_retry.py
kompoz/_temporal.py
kompoz/_tracing.py
kompoz/_transform.py
kompoz/_types.py
kompoz/_utility.py
kompoz/_validation.py
kompoz/py.typed
kompoz-0.2.4.dist-info/METADATA
kompoz-0.2.4.dist-info/WHEEL
kompoz-0.2.4.dist-info/licenses/LICENSE
kompoz-0.2.4.dist-info/RECORD
