Metadata-Version: 2.4
Name: kompoz
Version: 0.2.4
Summary: Composable predicate and transform combinators with operator overloading
Project-URL: Homepage, https://github.com/mtingers/kompoz
Project-URL: Repository, https://github.com/mtingers/kompoz
Project-URL: Documentation, https://github.com/mtingers/kompoz#readme
Project-URL: Bug Tracker, https://github.com/mtingers/kompoz/issues
Project-URL: Changelog, https://github.com/mtingers/kompoz/blob/main/CHANGELOG.md
Author-email: Matth Ingersoll <matth@mtingers.com>
License-Expression: MIT
License-File: LICENSE
Keywords: combinator,declarative,functional,pipeline,predicate,rules,transform,validation
Classifier: Development Status :: 4 - Beta
Classifier: Intended Audience :: Developers
Classifier: License :: OSI Approved :: MIT License
Classifier: Operating System :: OS Independent
Classifier: Programming Language :: Python :: 3
Classifier: Programming Language :: Python :: 3.13
Classifier: Programming Language :: Python :: 3.14
Classifier: Topic :: Software Development :: Libraries :: Python Modules
Classifier: Typing :: Typed
Requires-Python: >=3.13
Provides-Extra: dev
Requires-Dist: pre-commit>=4.0; extra == 'dev'
Requires-Dist: pyright>=1.1; extra == 'dev'
Requires-Dist: pytest-cov>=7.0.0; extra == 'dev'
Provides-Extra: opentelemetry
Requires-Dist: opentelemetry-api>=1.39.1; extra == 'opentelemetry'
Requires-Dist: opentelemetry-exporter-otlp>=1.39.1; extra == 'opentelemetry'
Requires-Dist: opentelemetry-sdk>=1.39.1; extra == 'opentelemetry'
